bw2_lcimpact/__init__.py
bw2_lcimpact/base.py
bw2_lcimpact/climate.py
bw2_lcimpact/land_use.py
bw2_lcimpact/main.py
bw2_lcimpact/pm.py
bw2_lcimpact/water.py
bw2_lcimpact/data/climate-change.xlsx
bw2_lcimpact/data/land_use.gpkg
bw2_lcimpact/data/particulate_matter.gpkg
bw2_lcimpact/data/water_eq_sw_core.gpkg
bw2_lcimpact/data/water_eq_sw_extended.gpkg
bw2_lcimpact/data/water_hh.gpkg
bw2_lcimpact-0.3.dist-info/DESCRIPTION.rst
bw2_lcimpact-0.3.dist-info/METADATA
bw2_lcimpact-0.3.dist-info/RECORD
bw2_lcimpact-0.3.dist-info/WHEEL
bw2_lcimpact-0.3.dist-info/metadata.json
bw2_lcimpact-0.3.dist-info/top_level.txt
