Metadata-Version: 2.0
Name: bw2-lcimpact
Version: 0.3
Summary: LC IMPACT regionalized LCIA method for Brightway2
Home-page: https://github.com/cmutel/bw2-lcimpact
Author: Chris Mutel
Author-email: cmutel@gmail.com
License: Copyright (c) 2017, Chris Mutel and Paul Scherrer Institut
Requires-Dist: brightway2
Requires-Dist: wrapt
Requires-Dist: xlrd
